{"Not Scraped": 283, "Has Ground Truth": {"work": {"Right": 0, "Tie": 0, "Wrong": 0, "Below Threshold": 103, "No Data": 12}, "college": {"Right": 34, "Tie": 85, "Wrong": 132, "Below Threshold": 61, "No Data": 9}, "highschool": {"Right": 249, "Tie": 9, "Wrong": 47, "Below Threshold": 11, "No Data": 6}, "cities": {"Right": 156, "Tie": 74, "Wrong": 123, "Below Threshold": 14, "No Data": 9}, "religiousviews": {"Right": 23, "Tie": 0, "Wrong": 30, "Below Threshold": 61, "No Data": 4}, "politicalviews": {"Right": 0, "Tie": 0, "Wrong": 0, "Below Threshold": 41, "No Data": 13}, "birthyear": {"Right": 3, "Tie": 2, "Wrong": 14, "Below Threshold": 148, "No Data": 33}}, "No Ground Truth": {"work": {"Tie": 0, "Below Threshold": 321, "No Data": 30}, "college": {"Tie": 44, "Below Threshold": 36, "No Data": 1}, "highschool": {"Tie": 5, "Below Threshold": 9, "No Data": 4}, "cities": {"Tie": 13, "Below Threshold": 3, "No Data": 2}, "religiousviews": {"Tie": 0, "Below Threshold": 192, "No Data": 29}, "politicalviews": {"Tie": 0, "Below Threshold": 284, "No Data": 129}, "birthyear": {"Tie": 0, "Below Threshold": 176, "No Data": 65}}}